indo_normalizer/Normalizer.py
indo_normalizer/__init__.py
indo_normalizer/functions.py
indo_normalizer/corpus/common_words.txt
indo_normalizer/corpus/slangs.csv
indo_normalizer-1.2.0.dist-info/METADATA
indo_normalizer-1.2.0.dist-info/WHEEL
indo_normalizer-1.2.0.dist-info/top_level.txt
indo_normalizer-1.2.0.dist-info/RECORD
