Metadata-Version: 2.4
Name: indo-normalizer
Version: 1.2.0
Summary: A Python library for normalizing Indonesian informal text (slang, leet, repetitions, typos).
Home-page: https://github.com/drestanto/indo-normalizer
Author: Drestanto Muhammad Dyasputro
Author-email: dyas@live.com
License: MIT
Classifier: Programming Language :: Python :: 3
Classifier: License :: OSI Approved :: MIT License
Classifier: Operating System :: OS Independent
Requires-Python: >=3.7
Requires-Dist: pandas>=1.0.0
Requires-Dist: rapidfuzz>=2.0.0
Provides-Extra: dev
Requires-Dist: pytest; extra == "dev"
Requires-Dist: twine; extra == "dev"
